exdoc/__init__.py
exdoc/data.py
exdoc/py/__init__.py
exdoc/sa/__init__.py
exdoc-0.1.4.post1.dist-info/LICENSE
exdoc-0.1.4.post1.dist-info/METADATA
exdoc-0.1.4.post1.dist-info/WHEEL
exdoc-0.1.4.post1.dist-info/top_level.txt
exdoc-0.1.4.post1.dist-info/RECORD
