Metadata-Version: 2.1
Name: exdoc
Version: 0.1.4.post1
Summary: Documentation extractor. 
Home-page: https://github.com/kolypto/py-exdoc
Author: Mark Vartanyan
Author-email: kolypto@gmail.com
License: BSD
Keywords: documentation
Platform: any
Classifier: Development Status :: 5 - Production/Stable
Classifier: Intended Audience :: Developers
Classifier: Natural Language :: English
Classifier: Operating System :: OS Independent
Classifier: Programming Language :: Python :: 3
Classifier: Topic :: Software Development :: Libraries :: Python Modules
Requires-Python: >=3.4
